odoo/addons/l10n_it_fiscal_payment_term/README.rst
odoo/addons/l10n_it_fiscal_payment_term/__init__.py
odoo/addons/l10n_it_fiscal_payment_term/__manifest__.py
odoo/addons/l10n_it_fiscal_payment_term/data/fatturapa_data.xml
odoo/addons/l10n_it_fiscal_payment_term/i18n/it.po
odoo/addons/l10n_it_fiscal_payment_term/i18n/l10n_it_fiscal_payment_term.pot
odoo/addons/l10n_it_fiscal_payment_term/models/__init__.py
odoo/addons/l10n_it_fiscal_payment_term/models/account.py
odoo/addons/l10n_it_fiscal_payment_term/readme/CONFIGURE.rst
odoo/addons/l10n_it_fiscal_payment_term/readme/CONTRIBUTORS.rst
odoo/addons/l10n_it_fiscal_payment_term/readme/DESCRIPTION.rst
odoo/addons/l10n_it_fiscal_payment_term/security/ir.model.access.csv
odoo/addons/l10n_it_fiscal_payment_term/static/description/icon.png
odoo/addons/l10n_it_fiscal_payment_term/static/description/index.html
odoo/addons/l10n_it_fiscal_payment_term/views/account_view.xml
odoo11_addon_l10n_it_fiscal_payment_term-11.0.1.2.0.dist-info/METADATA
odoo11_addon_l10n_it_fiscal_payment_term-11.0.1.2.0.dist-info/WHEEL
odoo11_addon_l10n_it_fiscal_payment_term-11.0.1.2.0.dist-info/top_level.txt
odoo11_addon_l10n_it_fiscal_payment_term-11.0.1.2.0.dist-info/RECORD
